{
  "type": "FeatureCollection",
  "features": [
    {
      "type": "Feature",
      "geometry": {
        "type": "Point",
        "coordinates": [
          -74.365944,
          40.498441
        ]
      },
      "properties": {
        "marker-symbol": "beer",
        "marker-color": "#607D8B",
        "marker-size": "small",
        "name": "Cypress Brewing Co.",
        "address": "30 Nixon Ln, Unit E, Edison, NJ 08837",
        "url": "http://cypressbrewing.com/",
        "geoBeerId": "0c186b09-6d76-49e3-b7eb-7e3b4e6dca39"
      }
    }
  ]
}
