{
  "type": "FeatureCollection",
  "features": [
    {
      "type": "Feature",
      "geometry": {
        "type": "Point",
        "coordinates": [
          -74.529617,
          39.447319
        ]
      },
      "properties": {
        "marker-symbol": "beer",
        "marker-color": "#607D8B",
        "marker-size": "small",
        "name": "Garden State Beer Company",
        "address": "247 E White Horse Pike, Galloway, NJ 08205",
        "url": "http://www.gardenstatebeerco.com/",
        "geoBeerId": "b85c3762-756b-4cfa-9024-f1fe6f32472f"
      }
    }
  ]
}
