{
  "type": "FeatureCollection",
  "features": [
    {
      "type": "Feature",
      "geometry": {
        "type": "Point",
        "coordinates": [
          -75.9523782,
          40.3356057
        ]
      },
      "properties": {
        "marker-symbol": "beer",
        "marker-color": "#607D8B",
        "marker-size": "small",
        "name": "Chatty Monks Brewing",
        "address": "610 Penn Ave, West Reading, PA 19611",
        "url": "http://chattymonks.com/",
        "geoBeerId": "5ca2f833-b03f-4e00-a431-d9e56a7c1a69"
      }
    }
  ]
}
