{
  "type": "FeatureCollection",
  "features": [
    {
      "type": "Feature",
      "geometry": {
        "type": "Point",
        "coordinates": [
          -75.5899183,
          39.9487565
        ]
      },
      "properties": {
        "marker-symbol": "beer",
        "marker-color": "#607D8B",
        "marker-size": "small",
        "name": "Levante Brewing",
        "address": "208 Carter Dr Suite 2, West Chester, PA 19382",
        "url": "http://levantebrewing.com/",
        "geoBeerId": "0c507272-6577-41ab-ad86-1986fdf3dc10"
      }
    }
  ]
}
