{
  "type": "FeatureCollection",
  "features": [
    {
      "type": "Feature",
      "geometry": {
        "type": "Point",
        "coordinates": [
          -76.349236,
          40.093749
        ]
      },
      "properties": {
        "marker-symbol": "beer",
        "marker-color": "#607D8B",
        "marker-size": "small",
        "name": "The Mad Chef Craft Brewing",
        "address": "2023 Miller Rd, East Petersburg, PA 17520",
        "url": "http://www.madchefcraftbrewing.com/",
        "geoBeerId": "b54c10c2-08f4-4db8-b9d6-9f523132e268"
      }
    }
  ]
}
