{
  "type": "FeatureCollection",
  "features": [
    {
      "type": "Feature",
      "geometry": {
        "type": "Point",
        "coordinates": [
          -75.493439,
          40.533774
        ]
      },
      "properties": {
        "marker-symbol": "beer",
        "marker-color": "#607D8B",
        "marker-size": "small",
        "name": "Yergey Brewing",
        "address": "518 Bank St, Emmaus, PA 18049",
        "url": "http://www.yergeybrewing.com/",
        "geoBeerId": "d53d5c2c-baee-4a22-a3ed-79905d172623"
      }
    }
  ]
}
