{
  "type": "FeatureCollection",
  "features": [
    {
      "type": "Feature",
      "geometry": {
        "type": "Point",
        "coordinates": [
          -75.0805256,
          38.3402733
        ]
      },
      "properties": {
        "marker-symbol": "beer",
        "marker-color": "#607D8B",
        "marker-size": "small",
        "name": "Backshore Brewing",
        "address": "913 Atlantic Ave, Ocean City, MD 21842",
        "url": "http://www.backshorebrew.com/",
        "geoBeerId": "d9533172-0194-45aa-a129-6e610f7e12e3"
      }
    }
  ]
}
