{
  "type": "FeatureCollection",
  "features": [
    {
      "type": "Feature",
      "geometry": {
        "type": "Point",
        "coordinates": [
          -74.927654,
          39.78979
        ]
      },
      "properties": {
        "marker-symbol": "beer",
        "marker-color": "#607D8B",
        "marker-size": "small",
        "name": "Berlin Brewing Company",
        "address": "220 S White Horse Pike, Berlin, NJ 08009",
        "url": "http://www.berlinbrewco.com/"
      }
    }
  ]
}
