{
  "type": "FeatureCollection",
  "features": [
    {
      "type": "Feature",
      "geometry": {
        "type": "Point",
        "coordinates": [
          -75.623784,
          39.280399
        ]
      },
      "properties": {
        "marker-symbol": "beer",
        "marker-color": "#607D8B",
        "marker-size": "small",
        "name": "Blue Earl Brewing Company",
        "address": "210 Artisan Dr, Smyrna, DE 19977",
        "url": "http://blueearlbrewing.com/",
        "geoBeerId": "74920167-8b6d-46e5-9cfa-6f41f16900f8"
      }
    }
  ]
}
