{
  "type": "FeatureCollection",
  "features": [
    {
      "type": "Feature",
      "geometry": {
        "type": "Point",
        "coordinates": [
          -76.730867,
          38.886284
        ]
      },
      "properties": {
        "marker-symbol": "beer",
        "marker-color": "#607D8B",
        "marker-size": "small",
        "name": "Calvert Brewing Company",
        "address": "15850 Commerce Ct, Upper Marlboro, MD 20774, USA",
        "url": "http://www.calvertbrewingcompany.com/"
      }
    }
  ]
}
