{
  "type": "FeatureCollection",
  "features": [
    {
      "type": "Feature",
      "geometry": {
        "type": "Point",
        "coordinates": [
          -76.221889,
          38.781061
        ]
      },
      "properties": {
        "marker-symbol": "beer",
        "marker-color": "#0047AB",
        "marker-size": "large",
        "name": "Eastern Shore Brewing Co",
        "address": "605 S Talbot St, Saint Michaels, MD",
        "url": "http://www.easternshorebrewing.com/",
        "geoBeerId": "d910862a-7b63-4ebe-a6af-9243befbcecd"
      }
    }
  ]
}
