{
  "type": "FeatureCollection",
  "features": [
    {
      "type": "Feature",
      "geometry": {
        "type": "Point",
        "coordinates": [
          -111.917409,
          33.419535
        ]
      },
      "properties": {
        "marker-symbol": "beer",
        "marker-color": "#607D8B",
        "marker-size": "small",
        "name": "Four Peaks Brewing Company (AB-InBev)",
        "address": "1340 East 8th Street, Tempe, AZ 85281",
        "url": "http://www.fourpeaks.com/"
      }
    }
  ]
}
