{
  "type": "FeatureCollection",
  "features": [
    {
      "type": "Feature",
      "geometry": {
        "type": "Point",
        "coordinates": [
          -71.832404,
          41.385139
        ]
      },
      "properties": {
        "marker-symbol": "beer",
        "marker-color": "#607D8B",
        "marker-size": "small",
        "name": "Grey Sail Brewing Company",
        "address": "63 Canal St, Westerly, RI 02891",
        "url": "http://greysailbrewing.com/",
        "geoBeerId": "638b620e-9df5-4b05-8cff-fd141525bd7d"
      }
    }
  ]
}
