{
  "type": "FeatureCollection",
  "features": [
    {
      "type": "Feature",
      "geometry": {
        "type": "Point",
        "coordinates": [
          -75.718722,
          40.247596
        ]
      },
      "properties": {
        "marker-symbol": "beer",
        "marker-color": "#607D8B",
        "marker-size": "small",
        "name": "Hidden River Brewing Company",
        "address": "1808 W Schuylkill Rd, Douglassville, PA 19518",
        "url": "http://hiddenriverbrewing.com/"
      }
    }
  ]
}
