{
  "type": "FeatureCollection",
  "features": [
    {
      "type": "Feature",
      "geometry": {
        "type": "Point",
        "coordinates": [
          -71.411417,
          42.280167
        ]
      },
      "properties": {
        "marker-symbol": "beer",
        "marker-color": "#607D8B",
        "marker-size": "small",
        "name": "Jack’s Abby Brewing",
        "address": "100 Clinton Street, Framingham, MA 01702",
        "url": "http://jacksabby.com/",
        "geoBeerId": "f758bff6-327e-485d-a22a-b02a2691c85a"
      }
    }
  ]
}
