{
  "type": "FeatureCollection",
  "features": [
    {
      "type": "Feature",
      "geometry": {
        "type": "Point",
        "coordinates": [
          -76.610422,
          39.324338
        ]
      },
      "properties": {
        "marker-symbol": "beer",
        "marker-color": "#607D8B",
        "marker-size": "small",
        "name": "Peabody Heights Brewery",
        "address": "401 East 30th Street, Baltimore, MD 21218",
        "url": "http://peabodyheightsbrewery.com/",
        "geoBeerId": "3627ce3d-1eb7-49d6-9b82-e005bd453ec6"
      }
    }
  ]
}
