{
  "type": "FeatureCollection",
  "features": [
    {
      "type": "Feature",
      "geometry": {
        "type": "Point",
        "coordinates": [
          -75.535232,
          40.194803
        ]
      },
      "properties": {
        "marker-symbol": "beer",
        "marker-color": "#0047AB",
        "marker-size": "large",
        "name": "Stickman Brews",
        "address": "326 N Lewis Rd #240, Royersford, PA 19468",
        "url": "http://stickmanbrews.com"
      }
    }
  ]
}
