{
  "type": "FeatureCollection",
  "features": [
    {
      "type": "Feature",
      "geometry": {
        "type": "Point",
        "coordinates": [
          -76.074506,
          40.237418
        ]
      },
      "properties": {
        "marker-symbol": "restaurant",
        "marker-color": "#607D8B",
        "marker-size": "small",
        "name": "Stoudt's Black Angus Restaurant & Pub",
        "address": "2800 N Reading Rd, Adamstown, PA 19501",
        "url": "http://stoudtsbeer.com",
        "geoBeerId": "b45f4a51-50ec-494a-9fab-27697246ad34"
      }
    }
  ]
}
