{
  "type": "FeatureCollection",
  "features": [
    {
      "type": "Feature",
      "geometry": {
        "type": "Point",
        "coordinates": [
          -93.140904,
          44.915537
        ]
      },
      "properties": {
        "marker-symbol": "beer",
        "marker-color": "#607D8B",
        "marker-size": "small",
        "name": "Summit Brewing Company",
        "address": "910 Montreal Circle, St. Paul, MN 55102",
        "url": "http://www.summitbrewing.com/",
        "geoBeerId": "2d42ed7e-7586-4364-a1ee-e428f31756f9"
      }
    }
  ]
}
