{
  "type": "FeatureCollection",
  "features": [
    {
      "type": "Feature",
      "geometry": {
        "type": "Point",
        "coordinates": [
          -74.274261,
          40.605873
        ]
      },
      "properties": {
        "marker-symbol": "beer",
        "marker-color": "#607D8B",
        "marker-size": "small",
        "name": "Wet Ticket Brewing, LLC.",
        "address": "1435 Main St, Rahway, NJ 07065",
        "url": "https://www.wetticketbrewing.com/"
      }
    }
  ]
}
