{
  "type": "FeatureCollection",
  "features": [
    {
      "type": "Feature",
      "geometry": {
        "type": "Point",
        "coordinates": [
          -76.1950815,
          40.6913896
        ]
      },
      "properties": {
        "marker-symbol": "beer",
        "marker-color": "#0047AB",
        "marker-size": "large",
        "name": "Yuengling Brewing Co.",
        "address": "501 Mahantongo St, Pottsville, PA 17901",
        "url": "http://yuengling.com",
        "geoBeerId": "3ea60a09-84c6-43e5-aac0-5698302927de"
      }
    }
  ]
}
